pyasyncserver/__init__.py
pyasyncserver/apps/__init__.py
pyasyncserver/apps/app.py
pyasyncserver/apps/odm_app.py
pyasyncserver/core/__init__.py
pyasyncserver/core/logger/__init__.py
pyasyncserver/pipes/__init__.py
pyasyncserver/pipes/directions.py
pyasyncserver/pipes/helpers.py
pyasyncserver/pipes/http_pipe.py
pyasyncserver/pipes/nats_pipe.py
pyasyncserver/pipes/pipe.py
pyasyncserver-0.1.5.dist-info/LICENSE
pyasyncserver-0.1.5.dist-info/METADATA
pyasyncserver-0.1.5.dist-info/WHEEL
pyasyncserver-0.1.5.dist-info/top_level.txt
pyasyncserver-0.1.5.dist-info/zip-safe
pyasyncserver-0.1.5.dist-info/RECORD
